imgrvt/__init__.py
imgrvt/generate.py
imgrvt/imgrvt.py
imgrvt-1.0.0.dist-info/LICENSE
imgrvt-1.0.0.dist-info/METADATA
imgrvt-1.0.0.dist-info/WHEEL
imgrvt-1.0.0.dist-info/top_level.txt
imgrvt-1.0.0.dist-info/RECORD
