Metadata-Version: 2.1
Name: imgrvt
Version: 1.0.0
Summary: Radial variance transform
Home-page: https://github.com/AlexShkarin/rvt
Author: Alexey Shkarin
Author-email: alex.shkarin@gmail.com
License: UNKNOWN
Project-URL: Documentation, https://github.com/AlexShkarin/rvt
Project-URL: Source, https://github.com/AlexShkarin/rvt
Project-URL: Tracker, https://github.com/AlexShkarin/rvt/issues
Platform: UNKNOWN
Classifier: Development Status :: 5 - Production/Stable
Classifier: Intended Audience :: Science/Research
Classifier: Topic :: Scientific/Engineering :: Image Processing
Classifier: License :: OSI Approved :: GNU General Public License v3 (GPLv3)
Classifier: Programming Language :: Python :: 3
Requires-Dist: numpy
Requires-Dist: scipy
